{
    "additions": [
        {
            "key": "added_param0",
            "value": "2453"
        },
        {
            "key": "added_param1",
            "value": "2634"
        },
        {
            "key": "added_param2",
            "value": "2587"
        },
        {
            "key": "added_param3",
            "value": "2934"
        },
        {
            "key": "added_param4",
            "value": "2778"
        },
        {
            "key": "added_param5",
            "value": "2043"
        },
        {
            "key": "added_param6",
            "value": "2661"
        },
        {
            "key": "added_param7",
            "value": "2719"
        },
        {
            "key": "added_param8",
            "value": "2118"
        },
        {
            "key": "added_param9",
            "value": "2613"
        },
        {
            "key": "added_param10",
            "value": "2815"
        },
        {
            "key": "added_param11",
            "value": "2075"
        },
        {
            "key": "added_param12",
            "value": "2607"
        },
        {
            "key": "added_param13",
            "value": "2758"
        },
        {
            "key": "added_param14",
            "value": "2427"
        },
        {
            "key": "added_param15",
            "value": "2887"
        },
        {
            "key": "added_param16",
            "value": "2367"
        },
        {
            "key": "added_param17",
            "value": "2498"
        },
        {
            "key": "added_param18",
            "value": "2892"
        }
    ],
    "deletions": [
        "param1",
        "param2",
        "param5",
        "param8",
        "param9",
        "param10",
        "param21",
        "param22",
        "param26",
        "param28",
        "param31",
        "param33",
        "param35",
        "param37",
        "param38",
        "param39",
        "param48",
        "param50",
        "param52",
        "param53",
        "param56",
        "param62",
        "param63",
        "param66",
        "param69",
        "param71",
        "param74",
        "param75",
        "param87",
        "param90",
        "param91",
        "param93",
        "param94",
        "param96",
        "param98"
    ],
    "updates": [
        {
            "key": "param0",
            "from": "781",
            "to": "1754"
        },
        {
            "key": "param3",
            "from": "9",
            "to": "1443"
        },
        {
            "key": "param4",
            "from": "326",
            "to": "1735"
        },
        {
            "key": "param12",
            "from": "664",
            "to": "1513"
        },
        {
            "key": "param16",
            "from": "211",
            "to": "1246"
        },
        {
            "key": "param18",
            "from": "811",
            "to": "1218"
        },
        {
            "key": "param19",
            "from": "368",
            "to": "1890"
        },
        {
            "key": "param23",
            "from": "488",
            "to": "1008"
        },
        {
            "key": "param25",
            "from": "488",
            "to": "1014"
        },
        {
            "key": "param27",
            "from": "628",
            "to": "1854"
        },
        {
            "key": "param29",
            "from": "397",
            "to": "1638"
        },
        {
            "key": "param30",
            "from": "987",
            "to": "1274"
        },
        {
            "key": "param36",
            "from": "229",
            "to": "1325"
        },
        {
            "key": "param42",
            "from": "180",
            "to": "1424"
        },
        {
            "key": "param44",
            "from": "967",
            "to": "1668"
        },
        {
            "key": "param47",
            "from": "291",
            "to": "1292"
        },
        {
            "key": "param51",
            "from": "576",
            "to": "1453"
        },
        {
            "key": "param54",
            "from": "792",
            "to": "1063"
        },
        {
            "key": "param55",
            "from": "916",
            "to": "1315"
        },
        {
            "key": "param57",
            "from": "236",
            "to": "1695"
        },
        {
            "key": "param59",
            "from": "957",
            "to": "1227"
        },
        {
            "key": "param60",
            "from": "402",
            "to": "1374"
        },
        {
            "key": "param61",
            "from": "523",
            "to": "1468"
        },
        {
            "key": "param68",
            "from": "641",
            "to": "1165"
        },
        {
            "key": "param73",
            "from": "361",
            "to": "2000"
        },
        {
            "key": "param78",
            "from": "562",
            "to": "1310"
        },
        {
            "key": "param84",
            "from": "410",
            "to": "1118"
        },
        {
            "key": "param85",
            "from": "442",
            "to": "1103"
        },
        {
            "key": "param88",
            "from": "708",
            "to": "1960"
        },
        {
            "key": "param97",
            "from": "625",
            "to": "1879"
        },
        {
            "key": "param99",
            "from": "945",
            "to": "1214"
        }
    ]
}